relycomply_cli/__init__.py
relycomply_cli/__main__.py
relycomply_cli/cleartoml.py
relycomply_cli/cli.py
relycomply_cli/generate_gql.py
relycomply_cli/helpers.py
relycomply_cli/rely.py
relycomply_cli-0.5.0.dist-info/entry_points.txt
relycomply_cli-0.5.0.dist-info/WHEEL
relycomply_cli-0.5.0.dist-info/METADATA
relycomply_cli-0.5.0.dist-info/RECORD
