Metadata-Version: 2.1
Name: relycomply-cli
Version: 0.5.0
Summary: The RelyComply Command Line Interface
Author: James Saunders
Author-email: james@businessoptics.biz
Requires-Python: >=3.8,<4.0
Classifier: Programming Language :: Python :: 3
Classifier: Programming Language :: Python :: 3.8
Classifier: Programming Language :: Python :: 3.9
Requires-Dist: dephell (>=0.8.3,<0.9.0)
Requires-Dist: fn_deps (>=0.1.0,<0.2.0)
Requires-Dist: gql (==3.0.0a1)
Requires-Dist: pygments (>=2.7.1,<3.0.0)
Requires-Dist: pygments-graphql (>=1.0.0,<2.0.0)
Requires-Dist: pyyaml
Requires-Dist: tabulate (>=0.8.7,<0.9.0)
Requires-Dist: termcolor (>=1.1.0,<2.0.0)
Requires-Dist: terminaltables (>=3.1.0,<4.0.0)
Requires-Dist: toml (>=0.10.1,<0.11.0)
